tests/__init__.py
tests/test_core.py
tests/test_dashboard.py
tests/test_imports.py
tests/test_utils.py
timeitPro/__init__.py
timeitPro/core.py
timeitPro/dashboard.py
timeitPro/utils.py
timeitpro-0.2.2.dist-info/licenses/LICENSE
timeitpro-0.2.2.dist-info/METADATA
timeitpro-0.2.2.dist-info/WHEEL
timeitpro-0.2.2.dist-info/entry_points.txt
timeitpro-0.2.2.dist-info/top_level.txt
timeitpro-0.2.2.dist-info/RECORD
