Metadata-Version: 2.4
Name: timeitPro
Version: 0.2.2
Summary: Advanced Python function profiler with JSON logging and Flask dashboard
Home-page: https://github.com/farahbakhsh3/timeitPro
Author: Farahbakhsh3
Author-email: farahbakhsh3@gmail.com
Classifier: Programming Language :: Python :: 3
Classifier: License :: OSI Approved :: GNU General Public License v3 (GPLv3)
Classifier: Operating System :: OS Independent
Requires-Python: >=3.9
License-File: LICENSE
Requires-Dist: Flask>=2.0.0
Requires-Dist: psutil>=5.9.0
Dynamic: author
Dynamic: author-email
Dynamic: classifier
Dynamic: description
Dynamic: description-content-type
Dynamic: home-page
Dynamic: license-file
Dynamic: requires-dist
Dynamic: requires-python
Dynamic: summary
